Zaraciccio/__init__.py
Zaraciccio/flask.py
Zaraciccio/input.py
Zaraciccio/locales.py
Zaraciccio/printer.py
Zaraciccio/sql.py
Zaraciccio-0.1.1.dist-info/LICENSE
Zaraciccio-0.1.1.dist-info/METADATA
Zaraciccio-0.1.1.dist-info/WHEEL
Zaraciccio-0.1.1.dist-info/top_level.txt
Zaraciccio-0.1.1.dist-info/RECORD
