Metadata-Version: 2.1
Name: Zaraciccio
Version: 0.1.1
Summary: Zaraciccio's Library for Python
Home-page: UNKNOWN
Author: Zaraciccio De Zaracicci
Author-email: zaradevelopment@outlook.com
License: UNKNOWN
Keywords: Zaraciccio
Platform: UNKNOWN
Classifier: Intended Audience :: Developers
Classifier: Programming Language :: Python
Classifier: Programming Language :: Python :: 3
Classifier: Topic :: Software Development :: Libraries :: Python Modules
Requires-Dist: setuptools (>=42)
Requires-Dist: wheel
